calculus/__init__.py
calculus/_calculus_core.cpython-311-darwin.so
calculus/bindings.cpp
calculus/core.cpp
calculus/differentiation.hpp
calculus/integration.hpp
calculus/limits.hpp
calculus/series.hpp
calculuslibrary-1.0.0.dist-info/METADATA
calculuslibrary-1.0.0.dist-info/WHEEL
calculuslibrary-1.0.0.dist-info/licenses/LICENSE
calculuslibrary-1.0.0.dist-info/RECORD
