Metadata-Version: 2.2
Name: calculuslibrary
Version: 1.0.0
Summary: A high-performance calculus library for Python with C++ backend
Keywords: calculus,mathematics,differentiation,integration,numerical-methods
Author-Email: Aditya Palit <adityapalit16@gmail.com>
License: MIT
Classifier: Development Status :: 4 - Beta
Classifier: Intended Audience :: Science/Research
Classifier: Intended Audience :: Developers
Classifier: Intended Audience :: Education
Classifier: License :: OSI Approved :: MIT License
Classifier: Programming Language :: Python :: 3
Classifier: Programming Language :: Python :: 3.8
Classifier: Programming Language :: Python :: 3.9
Classifier: Programming Language :: Python :: 3.10
Classifier: Programming Language :: Python :: 3.11
Classifier: Programming Language :: Python :: 3.12
Classifier: Programming Language :: C++
Classifier: Topic :: Scientific/Engineering :: Mathematics
Classifier: Operating System :: OS Independent
Project-URL: Homepage, https://github.com/epicvstuff/calculuslibrary
Project-URL: Documentation, https://github.com/epicvstuff/calculuslibrary#readme
Project-URL: Repository, https://github.com/epicvstuff/calculuslibrary
Requires-Python: >=3.8
Provides-Extra: test
Requires-Dist: pytest>=7.0; extra == "test"
Provides-Extra: dev
Requires-Dist: pytest>=7.0; extra == "dev"
Requires-Dist: build; extra == "dev"
Requires-Dist: twine; extra == "dev"
